compute_sha.py
git_remote_rclone_reds-0.3.data/scripts/git-remote-rclone
git_remote_rclone_reds-0.3.dist-info/licenses/LICENSE
git_remote_rclone_reds-0.3.dist-info/METADATA
git_remote_rclone_reds-0.3.dist-info/WHEEL
git_remote_rclone_reds-0.3.dist-info/top_level.txt
git_remote_rclone_reds-0.3.dist-info/RECORD
