Metadata-Version: 2.4
Name: git_remote_rclone_reds
Version: 0.3
Summary: Git remote helper for rclone-supported services
Home-page: https://github.com/redstreet/git-remote-rclone-reds
Author: Red S
Author-email: redstreet@users.noreply.github.com
Maintainer: Red S
Maintainer-email: redstreet@users.noreply.github.com
License: GPL-3.0
Classifier: Programming Language :: Python
Classifier: License :: OSI Approved :: GNU General Public License v3 (GPLv3)
Classifier: Programming Language :: Python :: 3
Requires-Python: >=3.5
License-File: LICENSE
Dynamic: license-file
